<problem>
  <text>
    <script type="loncapa/python">
# random variables
import random
a = random.randrange(4,9,1)

# Solutions with variables converted to string
# Make sure you name the solution with part id at the end. e.g. 'solution1' will be solution for part 1.
solution1 = "fact(3)"
solution2 = "{0}fact()".format(a)

    </script>


<ul>
<li>How many strings of length 3 can be formed by rearranging the letters "CAB"? (Order matters.)</li>
</ul>
    <numericalresponse answer="$solution1">
      <formulaequationinput/>
    </numericalresponse>

<ul>
<li>A pianist plans to play $a different pieces at a recital.</li>
</ul>
<p>In how many ways can she arrange these pieces in the program?</p>
    <numericalresponse answer="$solution2">
      <formulaequationinput/>
    </numericalresponse>


  </text>
</problem>
